nonebot_plugin_suggarex_cf/__init__.py
nonebot_plugin_suggarex_cf/core.py
nonebot_plugin_suggarex_cf-2.0.0.dist-info/licenses/LICENSE
nonebot_plugin_suggarex_cf-2.0.0.dist-info/METADATA
nonebot_plugin_suggarex_cf-2.0.0.dist-info/WHEEL
nonebot_plugin_suggarex_cf-2.0.0.dist-info/top_level.txt
nonebot_plugin_suggarex_cf-2.0.0.dist-info/RECORD
