Metadata-Version: 2.4
Name: nonebot_plugin_suggarex_cf
Version: 2.0.0
Summary: 适用于SuggarChat插件的CloudFlare协议适配器实现，SuggarChat附属插件
Author-email: JohnRichard4096 <windowserror@163.com>
License: GPL-3.0-or-later
Project-URL: Homepage, https://github.com/LiteSuggarDEV/nonebot_plugin_suggarex_cf
Project-URL: Source, https://github.com/LiteSuggarDEV/nonebot_plugin_suggarex_cf
Project-URL: Issue Tracker, https://github.com/LiteSuggarDEV/nonebot_plugin_suggarex_cf/issues
Keywords: chat", "suggar", "nonebot
Requires-Python: <4.0,>=3.10
License-File: LICENSE
Requires-Dist: nonebot2>=2.2.0
Requires-Dist: nonebot-plugin-suggarchat>=3.2.0
Requires-Dist: nonebot-adapter-onebot>=2.0.0
Requires-Dist: aiohttp>=3.9.0
Requires-Dist: multidict>6.3.2
Dynamic: license-file
